echoss_fileformat/__init__.py
echoss_fileformat/csv_handler.py
echoss_fileformat/echoss_logger.py
echoss_fileformat/excel_handler.py
echoss_fileformat/feather_handler.py
echoss_fileformat/fileformat.py
echoss_fileformat/fileformat_base.py
echoss_fileformat/json_handler.py
echoss_fileformat/xml_handler.py
echoss_fileformat-1.2.9.dist-info/METADATA
echoss_fileformat-1.2.9.dist-info/WHEEL
echoss_fileformat-1.2.9.dist-info/top_level.txt
echoss_fileformat-1.2.9.dist-info/RECORD
