Metadata-Version: 2.4
Name: echoss-fileformat
Version: 1.2.9
Summary: File format handler packages for JSON, CSV, XML, and Excel files
Classifier: Programming Language :: Python :: 3
Classifier: Operating System :: OS Independent
Requires-Python: >=3.8
Requires-Dist: pandas>=1.5.3
Requires-Dist: numpy>=1.22.3
Requires-Dist: pyarrow<16,>=4.0.0
Requires-Dist: openpyxl>=3.1.0
Requires-Dist: xlrd>=1.2.0
Requires-Dist: lxml>=5.0.1
Requires-Dist: pyyaml>6.0.2
Provides-Extra: dev
Requires-Dist: pytest; extra == "dev"
